kumo/cmd/__init__.py
kumo/cmd/build.py
kumo/cmd/cli.py
kumo/cmd/deploy.py
kumo/cmd/init.py
kumo/cmd/step.py
kumo/cmd/system.py
kumo/cmd/version.py
kumo/internal/__init__.py
kumo/internal/builder.py
kumo/internal/config.py
kumo/internal/logger.py
kumo/model/__init__.py
kumo/model/config/__init__.py
kumo/model/config/base.py
kumo/model/config/builder.py
kumo/model/config/proxy.py
kumo/model/config/registry.py
kumo/model/config/role.py
kumo/model/config/ssh.py
kumo/model/connection.py
kumo/template/config.j2
kumo/utils/__init__.py
kumo/utils/common.py
kumo/utils/constants.py
kumo/utils/docker.py
kumo_cli-0.3.1.dist-info/LICENSE
kumo_cli-0.3.1.dist-info/METADATA
kumo_cli-0.3.1.dist-info/WHEEL
kumo_cli-0.3.1.dist-info/entry_points.txt
kumo_cli-0.3.1.dist-info/RECORD
