Metadata-Version: 2.1
Name: kumo-cli
Version: 0.3.1
Summary: Ferramenta CLI para build e deploy em orquestradores de containers
Home-page: https://github.com/LHForceTech/kumo
License: MIT
Author: Diego Lopes
Author-email: djkakaroto@gmail.com
Maintainer: LH Force Tech
Requires-Python: >=3.12,<4.0
Classifier: License :: OSI Approved :: MIT License
Classifier: Programming Language :: Python :: 3
Classifier: Programming Language :: Python :: 3.12
Classifier: Programming Language :: Python :: 3.13
Requires-Dist: docker (>=7.1.0,<8.0.0)
Requires-Dist: fabric (>=3.2.2,<4.0.0)
Requires-Dist: jinja2 (>=3.1.4,<4.0.0)
Requires-Dist: pydantic (>=2.9.2,<3.0.0)
Requires-Dist: pyyaml (>=6.0.2,<7.0.0)
Requires-Dist: typer (>=0.12.5,<0.13.0)
Project-URL: Repository, https://github.com/LHForceTech/kumo
